ragu/__init__.py
ragu/config.py
ragu/raguError.py
ragu/bin/ragu.py
ragu/dat/mars/mega90n000eb.tif
ragu/ingest/__init__.py
ragu/ingest/ingest_cresis_rds.py
ragu/ingest/ingest_cresis_snow.py
ragu/ingest/ingest_groundhog.py
ragu/ingest/ingest_gssi.py
ragu/ingest/ingest_lrs.py
ragu/ingest/ingest_marsis.py
ragu/ingest/ingest_marsis_ipc.py
ragu/ingest/ingest_oibAK.py
ragu/ingest/ingest_pulseekko.py
ragu/ingest/ingest_rimfax.py
ragu/ingest/ingest_sharad.py
ragu/ingest/ingest_template.py
ragu/ingest/ingest_uaf_kentech.py
ragu/nav/__init__.py
ragu/nav/gps.py
ragu/nav/navparse.py
ragu/radar/__init__.py
ragu/radar/flags.py
ragu/radar/pick.py
ragu/radar/processing.py
ragu/recs/20190928-235534_compiled.jpg
ragu/recs/basemap_icon.png
ragu/recs/bulb.jpg
ragu/recs/ragu_logo.png
ragu/tools/__init__.py
ragu/tools/constants.py
ragu/tools/export.py
ragu/tools/utils.py
ragu/ui/__init__.py
ragu/ui/basemap.py
ragu/ui/gui.py
ragu/ui/impick.py
ragu/ui/notepad.py
ragu/ui/wvpick.py
ragu-0.1.56.dist-info/LICENSE.txt
ragu-0.1.56.dist-info/METADATA
ragu-0.1.56.dist-info/WHEEL
ragu-0.1.56.dist-info/entry_points.txt
ragu-0.1.56.dist-info/top_level.txt
ragu-0.1.56.dist-info/RECORD
