Metadata-Version: 2.1
Name: ragu
Version: 0.1.56
Summary: Radar Analysis Graphical Utility (RAGU)
Author-email: Brandon Tober <tobers.brandon@gmail.com>, Michael Christoffersen <mchristo28@gmail.com>
License: GNU GENERAL PUBLIC LICENSE
Project-URL: documentation, https://github.com/btobers/ragu/wiki
Project-URL: repository, https://github.com/btobers/ragu
Classifier: Programming Language :: Python :: 3
Requires-Python: >=3.6
License-File: LICENSE.txt
Requires-Dist: pandas
Requires-Dist: numpy
Requires-Dist: scipy
Requires-Dist: matplotlib
Requires-Dist: rasterio
Requires-Dist: pyproj
Requires-Dist: tk
Requires-Dist: h5py
Requires-Dist: geopandas
